README.md
setup.py
unitts/__init__.py
unitts/basedriver.py
unitts/engine.py
unitts/version.py
unitts/voice.py
unitts.egg-info/PKG-INFO
unitts.egg-info/SOURCES.txt
unitts.egg-info/dependency_links.txt
unitts.egg-info/top_level.txt