Metadata-Version: 2.1
Name: unitts
Version: 0.0.8
Summary: unitts is a api for tts engine
Home-page: https://github.com/yumoqing/unitts
Author: yumoqing
Author-email: yumoqing@gmail.com
Platform: any
Classifier: Operating System :: OS Independent
Classifier: Programming Language :: Python :: 3
Classifier: License :: OSI Approved :: MIT License
